README.rst
setup.py
dedup_hash/__init__.py
dedup_hash/dedup_hash.py
dedup_hash.egg-info/PKG-INFO
dedup_hash.egg-info/SOURCES.txt
dedup_hash.egg-info/dependency_links.txt
dedup_hash.egg-info/entry_points.txt
dedup_hash.egg-info/requires.txt
dedup_hash.egg-info/top_level.txt
test/test_dedup_hash.py