Metadata-Version: 1.1
Name: dedup-hash
Version: 0.1.1
Summary: Finds and discards exact duplicate reads in fastq files.
Home-page: https://github.com/mvdbeek/dedup_hash
Author: Marius van den Beek
Author-email: m.vandenbeek@gmail.com
License: MIT
Keywords: Bioinformatics
Platform: UNKNOWN
Classifier: Development Status :: 5 - Production/Stable
Classifier: Intended Audience :: Developers
Classifier: Environment :: Console
Classifier: Operating System :: POSIX
Classifier: Topic :: Scientific/Engineering :: Bio-Informatics
Classifier: Natural Language :: English
Classifier: Programming Language :: Python :: 2
Classifier: Programming Language :: Python :: 2.7
